LICENSE
progo/__init__.py
progo/ble/constants.py
progo/ble/util.py
progo/constants.py
progo/exceptions.py
progo/params.py
progo/progo.py
progo/settings.py
progo/status.py
progo-0.1.8.dist-info/LICENSE
progo-0.1.8.dist-info/WHEEL
progo-0.1.8.dist-info/METADATA
progo-0.1.8.dist-info/RECORD
