Metadata-Version: 2.1
Name: progo
Version: 0.1.8
Summary: Upside-Down and Backwards™ GoPro - Control your GoPro Hero10.
Home-page: https://github.com/jakthom/progo
License: MIT
Keywords: gopro,camera,control
Author: Jakthom
Author-email: jake@bostata.com
Requires-Python: >=3.9,<3.11
Classifier: License :: OSI Approved :: MIT License
Classifier: Programming Language :: Python :: 3
Classifier: Programming Language :: Python :: 3.9
Requires-Dist: attrs (>=21.2.0,<22.0.0)
Requires-Dist: bleak (>=0.12.1,<0.13.0)
Requires-Dist: construct (>=2.10.67,<3.0.0)
Requires-Dist: loguru (>=0.5.3,<0.6.0)
Requires-Dist: numpy (>=1.21.2,<2.0.0)
Requires-Dist: opencv-python (>=4.5.3,<5.0.0)
Requires-Dist: packaging (>=21.2,<22.0)
Requires-Dist: requests (>=2.26.0,<3.0.0)
Requires-Dist: wireless (>=0.3.3,<0.4.0)
Project-URL: Repository, https://github.com/jakthom/progo
